{
  "id": "11fa829c-6c04-4c61-adb6-3059c626affa",
  "prevId": "00000000-0000-0000-0000-000000000000",
  "version": "7",
  "dialect": "postgresql",
  "tables": {
    "public.account": {
      "name": "account",
      "schema": "",
      "columns": {
        "id": {
          "name": "id",
          "type": "text",
          "primaryKey": true,
          "notNull": true
        },
        "account_id": {
          "name": "account_id",
          "type": "text",
          "primaryKey": false,
          "notNull": true
        },
        "provider_id": {
          "name": "provider_id",
          "type": "text",
          "primaryKey": false,
          "notNull": true
        },
        "user_id": {
          "name": "user_id",
          "type": "text",
          "primaryKey": false,
          "notNull": true
        },
        "access_token": {
          "name": "access_token",
          "type": "text",
          "primaryKey": false,
          "notNull": false
        },
        "refresh_token": {
          "name": "refresh_token",
          "type": "text",
          "primaryKey": false,
          "notNull": false
        },
        "id_token": {
          "name": "id_token",
          "type": "text",
          "primaryKey": false,
          "notNull": false
        },
        "access_token_expires_at": {
          "name": "access_token_expires_at",
          "type": "timestamp",
          "primaryKey": false,
          "notNull": false
        },
        "refresh_token_expires_at": {
          "name": "refresh_token_expires_at",
          "type": "timestamp",
          "primaryKey": false,
          "notNull": false
        },
        "scope": {
          "name": "scope",
          "type": "text",
          "primaryKey": false,
          "notNull": false
        },
        "password": {
          "name": "password",
          "type": "text",
          "primaryKey": false,
          "notNull": false
        },
        "created_at": {
          "name": "created_at",
          "type": "timestamp",
          "primaryKey": false,
          "notNull": true
        },
        "updated_at": {
          "name": "updated_at",
          "type": "timestamp",
          "primaryKey": false,
          "notNull": true
        }
      },
      "indexes": {},
      "foreignKeys": {
        "account_user_id_user_id_fk": {
          "name": "account_user_id_user_id_fk",
          "tableFrom": "account",
          "tableTo": "user",
          "columnsFrom": [
            "user_id"
          ],
          "columnsTo": [
            "id"
          ],
          "onDelete": "cascade",
          "onUpdate": "no action"
        }
      },
      "compositePrimaryKeys": {},
      "uniqueConstraints": {},
      "policies": {},
      "checkConstraints": {},
      "isRLSEnabled": false
    },
    "public.pg-drizzle_post": {
      "name": "pg-drizzle_post",
      "schema": "",
      "columns": {
        "id": {
          "name": "id",
          "type": "integer",
          "primaryKey": true,
          "notNull": true,
          "identity": {
            "type": "byDefault",
            "name": "pg-drizzle_post_id_seq",
            "schema": "public",
            "increment": "1",
            "startWith": "1",
            "minValue": "1",
            "maxValue": "2147483647",
            "cache": "1",
            "cycle": false
          }
        },
        "name": {
          "name": "name",
          "type": "varchar(256)",
          "primaryKey": false,
          "notNull": false
        },
        "createdById": {
          "name": "createdById",
          "type": "varchar(255)",
          "primaryKey": false,
          "notNull": true
        },
        "createdAt": {
          "name": "createdAt",
          "type": "timestamp with time zone",
          "primaryKey": false,
          "notNull": true
        },
        "updatedAt": {
          "name": "updatedAt",
          "type": "timestamp with time zone",
          "primaryKey": false,
          "notNull": false
        }
      },
      "indexes": {
        "created_by_idx": {
          "name": "created_by_idx",
          "columns": [
            {
              "expression": "createdById",
              "isExpression": false,
              "asc": true,
              "nulls": "last"
            }
          ],
          "isUnique": false,
          "concurrently": false,
          "method": "btree",
          "with": {}
        },
        "name_idx": {
          "name": "name_idx",
          "columns": [
            {
              "expression": "name",
              "isExpression": false,
              "asc": true,
              "nulls": "last"
            }
          ],
          "isUnique": false,
          "concurrently": false,
          "method": "btree",
          "with": {}
        }
      },
      "foreignKeys": {
        "pg-drizzle_post_createdById_user_id_fk": {
          "name": "pg-drizzle_post_createdById_user_id_fk",
          "tableFrom": "pg-drizzle_post",
          "tableTo": "user",
          "columnsFrom": [
            "createdById"
          ],
          "columnsTo": [
            "id"
          ],
          "onDelete": "no action",
          "onUpdate": "no action"
        }
      },
      "compositePrimaryKeys": {},
      "uniqueConstraints": {},
      "policies": {},
      "checkConstraints": {},
      "isRLSEnabled": false
    },
    "public.session": {
      "name": "session",
      "schema": "",
      "columns": {
        "id": {
          "name": "id",
          "type": "text",
          "primaryKey": true,
          "notNull": true
        },
        "expires_at": {
          "name": "expires_at",
          "type": "timestamp",
          "primaryKey": false,
          "notNull": true
        },
        "token": {
          "name": "token",
          "type": "text",
          "primaryKey": false,
          "notNull": true
        },
        "created_at": {
          "name": "created_at",
          "type": "timestamp",
          "primaryKey": false,
          "notNull": true
        },
        "updated_at": {
          "name": "updated_at",
          "type": "timestamp",
          "primaryKey": false,
          "notNull": true
        },
        "ip_address": {
          "name": "ip_address",
          "type": "text",
          "primaryKey": false,
          "notNull": false
        },
        "user_agent": {
          "name": "user_agent",
          "type": "text",
          "primaryKey": false,
          "notNull": false
        },
        "user_id": {
          "name": "user_id",
          "type": "text",
          "primaryKey": false,
          "notNull": true
        }
      },
      "indexes": {},
      "foreignKeys": {
        "session_user_id_user_id_fk": {
          "name": "session_user_id_user_id_fk",
          "tableFrom": "session",
          "tableTo": "user",
          "columnsFrom": [
            "user_id"
          ],
          "columnsTo": [
            "id"
          ],
          "onDelete": "cascade",
          "onUpdate": "no action"
        }
      },
      "compositePrimaryKeys": {},
      "uniqueConstraints": {
        "session_token_unique": {
          "name": "session_token_unique",
          "nullsNotDistinct": false,
          "columns": [
            "token"
          ]
        }
      },
      "policies": {},
      "checkConstraints": {},
      "isRLSEnabled": false
    },
    "public.user": {
      "name": "user",
      "schema": "",
      "columns": {
        "id": {
          "name": "id",
          "type": "text",
          "primaryKey": true,
          "notNull": true
        },
        "name": {
          "name": "name",
          "type": "text",
          "primaryKey": false,
          "notNull": true
        },
        "email": {
          "name": "email",
          "type": "text",
          "primaryKey": false,
          "notNull": true
        },
        "email_verified": {
          "name": "email_verified",
          "type": "boolean",
          "primaryKey": false,
          "notNull": true
        },
        "image": {
          "name": "image",
          "type": "text",
          "primaryKey": false,
          "notNull": false
        },
        "created_at": {
          "name": "created_at",
          "type": "timestamp",
          "primaryKey": false,
          "notNull": true
        },
        "updated_at": {
          "name": "updated_at",
          "type": "timestamp",
          "primaryKey": false,
          "notNull": true
        }
      },
      "indexes": {},
      "foreignKeys": {},
      "compositePrimaryKeys": {},
      "uniqueConstraints": {
        "user_email_unique": {
          "name": "user_email_unique",
          "nullsNotDistinct": false,
          "columns": [
            "email"
          ]
        }
      },
      "policies": {},
      "checkConstraints": {},
      "isRLSEnabled": false
    },
    "public.verification": {
      "name": "verification",
      "schema": "",
      "columns": {
        "id": {
          "name": "id",
          "type": "text",
          "primaryKey": true,
          "notNull": true
        },
        "identifier": {
          "name": "identifier",
          "type": "text",
          "primaryKey": false,
          "notNull": true
        },
        "value": {
          "name": "value",
          "type": "text",
          "primaryKey": false,
          "notNull": true
        },
        "expires_at": {
          "name": "expires_at",
          "type": "timestamp",
          "primaryKey": false,
          "notNull": true
        },
        "created_at": {
          "name": "created_at",
          "type": "timestamp",
          "primaryKey": false,
          "notNull": false
        },
        "updated_at": {
          "name": "updated_at",
          "type": "timestamp",
          "primaryKey": false,
          "notNull": false
        }
      },
      "indexes": {},
      "foreignKeys": {},
      "compositePrimaryKeys": {},
      "uniqueConstraints": {},
      "policies": {},
      "checkConstraints": {},
      "isRLSEnabled": false
    }
  },
  "enums": {},
  "schemas": {},
  "sequences": {},
  "roles": {},
  "policies": {},
  "views": {},
  "_meta": {
    "columns": {},
    "schemas": {},
    "tables": {}
  }
}